gamms/__init__.py
gamms/context.py
gamms/internal_context.py
gamms/osm.py
gamms/AgentEngine/__init__.py
gamms/AgentEngine/agent_engine.py
gamms/C/MessageEngine/Makefile
gamms/C/MessageEngine/redis_interface.c
gamms/C/MessageEngine/redis_interface.h
gamms/ComputationEngine/__init__.py
gamms/ComputationEngine/compute_egine.py
gamms/GraphEngine/__init__.py
gamms/GraphEngine/graph_engine.py
gamms/MemoryEngine/memory_engine.py
gamms/MemoryEngine/store.py
gamms/MessageEngine/message_engine.py
gamms/MessageEngine/redis_message.py
gamms/Recorder/__init__.py
gamms/Recorder/component.py
gamms/Recorder/recorder.py
gamms/SensorEngine/__init__.py
gamms/SensorEngine/sensor_engine.py
gamms/VisualizationEngine/__init__.py
gamms/VisualizationEngine/artist.py
gamms/VisualizationEngine/builtin_artists.py
gamms/VisualizationEngine/default_drawers.py
gamms/VisualizationEngine/no_engine.py
gamms/VisualizationEngine/pygame_engine.py
gamms/VisualizationEngine/render_manager.py
gamms/VisualizationEngine/utils.py
gamms/typing/__init__.py
gamms/typing/agent_engine.py
gamms/typing/artist.py
gamms/typing/compute_engine.py
gamms/typing/context.py
gamms/typing/graph_engine.py
gamms/typing/internal_context.py
gamms/typing/logger.py
gamms/typing/memory_engine.py
gamms/typing/message_engine.py
gamms/typing/opcodes.py
gamms/typing/recorder.py
gamms/typing/sensor_engine.py
gamms/typing/visualization_engine.py
gamms-0.2.6.dist-info/licenses/LICENSE
gamms-0.2.6.dist-info/METADATA
gamms-0.2.6.dist-info/WHEEL
gamms-0.2.6.dist-info/top_level.txt
gamms-0.2.6.dist-info/RECORD
