Metadata-Version: 2.4
Name: gamms
Version: 0.2.6
Summary: GAMMS (Graph based Adversarial Multiagent Modelling Simulator) is a Python library designed for simulating large scale multi-agent scenarios on environments represented as graphs
Author: Andre Dion, Xiao Jiang
Author-email: Rohan Patil <rpatil@ucsd.edu>, Jai Malegaonkar <jmalegaonkar@ucsd.edu>
License-Expression: Apache-2.0
Project-URL: Homepage, https://gammsim.github.io/gamms
Project-URL: Repository, https://github.com/gammsim/gamms
Project-URL: Bug Tracker, https://github.com/gammsim/gamms/issues
Keywords: multi-agent,simulation,graphs,adversarial
Classifier: Development Status :: 3 - Alpha
Classifier: Programming Language :: Python :: 3.9
Classifier: Programming Language :: Python :: 3.10
Classifier: Programming Language :: Python :: 3.11
Classifier: Intended Audience :: Developers
Classifier: Intended Audience :: Science/Research
Classifier: Operating System :: OS Independent
Requires-Python: >=3.9
License-File: LICENSE
Requires-Dist: pygame
Requires-Dist: shapely
Requires-Dist: networkx
Requires-Dist: cbor2
Requires-Dist: aenum
Requires-Dist: osmnx
Provides-Extra: docs
Requires-Dist: mkdocs-material; extra == "docs"
Dynamic: license-file
